Metadata-Version: 1.1
Name: aiofiles38
Version: 0.5.0.dev0
Summary: this will be removed after the origin aiofiles38 supports new versions of Python 
Home-page: https://github.com/kasheemlew/aiofiles
Author: Tin Tvrtkovic
Author-email: tinchester@gmail.com
License: Apache 2.0
Platform: UNKNOWN
Classifier: Development Status :: 4 - Beta
Classifier: Intended Audience :: Developers
Classifier: License :: OSI Approved :: Apache Software License
Classifier: Programming Language :: Python :: 3.5
Classifier: Programming Language :: Python :: 3.6
Classifier: Programming Language :: Python :: 3.7
Classifier: Programming Language :: Python :: 3.8
Classifier: Topic :: System :: Filesystems
